bqplot_gl/__init__.py
bqplot_gl-0.0.0.dist-info/LICENSE
bqplot_gl-0.0.0.dist-info/METADATA
bqplot_gl-0.0.0.dist-info/WHEEL
bqplot_gl-0.0.0.dist-info/top_level.txt
bqplot_gl-0.0.0.dist-info/RECORD
